tempowork/CIG.py
tempowork/CIG_edge.py
tempowork/CIG_node.py
tempowork/IT.py
tempowork/IT_nil.py
tempowork/IT_node.py
tempowork/__init__.py
tempowork/tempowork.py
tempowork-0.1.5.dist-info/LICENSE
tempowork-0.1.5.dist-info/WHEEL
tempowork-0.1.5.dist-info/METADATA
tempowork-0.1.5.dist-info/RECORD
