Metadata-Version: 2.1
Name: tempowork
Version: 0.1.5
Summary: A library for mining temporal networks where time is represented as a continuous dimension!
License: MIT
Author: alijazayeri
Author-email: jazayeri.ali@gmail.com
Requires-Python: >=3.10,<4.0
Classifier: License :: OSI Approved :: MIT License
Classifier: Programming Language :: Python :: 3
Classifier: Programming Language :: Python :: 3.10
